rest_envelope/__init__.py
rest_envelope/mixins.py
django_rest_envelope-1.1.0.dist-info/LICENCE
django_rest_envelope-1.1.0.dist-info/METADATA
django_rest_envelope-1.1.0.dist-info/WHEEL
django_rest_envelope-1.1.0.dist-info/top_level.txt
django_rest_envelope-1.1.0.dist-info/RECORD
