Metadata-Version: 2.1
Name: django-rest-envelope
Version: 1.1.0
Summary: A mixin for Django REST package List Views to return an object instead of a list.
Author-email: Ferran Jovell <ferran.jovell+gh@gmail.com>
Project-URL: homepage, https://github.com/mrswats/django-rest-envelope
Project-URL: Bug Tracker, https://github.com/mrswats/django-rest-envelope/issues
Keywords: django
Classifier: Intended Audience :: Developers
Classifier: License :: OSI Approved :: MIT License
Classifier: Programming Language :: Python :: 3.8
Classifier: Programming Language :: Python :: 3.9
Classifier: Programming Language :: Python :: 3.10
Classifier: Programming Language :: Python :: 3.11
Classifier: Operating System :: OS Independent
Classifier: Topic :: Software Development :: Libraries
Classifier: Environment :: Web Environment
Classifier: Framework :: Django
Requires-Python: >=3.9
License-File: LICENCE
Requires-Dist: Django >=4.1.1
Requires-Dist: djangorestframework >=3.11.0
Provides-Extra: test
Requires-Dist: pytest ; extra == 'test'
Requires-Dist: pytest-django ; extra == 'test'
